notionmanager/.config/env.example
notionmanager/.config/fonts/coresansc/coresansc15.otf
notionmanager/.config/fonts/coresansc/coresansc15it.otf
notionmanager/.config/fonts/coresansc/coresansc25.otf
notionmanager/.config/fonts/coresansc/coresansc25it.otf
notionmanager/.config/fonts/coresansc/coresansc35.otf
notionmanager/.config/fonts/coresansc/coresansc35it.otf
notionmanager/.config/fonts/coresansc/coresansc45.otf
notionmanager/.config/fonts/coresansc/coresansc45it.otf
notionmanager/.config/fonts/coresansc/coresansc55.otf
notionmanager/.config/fonts/coresansc/coresansc55it.otf
notionmanager/.config/fonts/coresansc/coresansc65.otf
notionmanager/.config/fonts/coresansc/coresansc65it.otf
notionmanager/.config/fonts/coresansc/coresansc75.otf
notionmanager/.config/fonts/coresansc/coresansc75it.otf
notionmanager/.config/fonts/coresansc/coresansc85.otf
notionmanager/.config/fonts/coresansc/coresansc85it.otf
notionmanager/.config/fonts/coresansc/coresansc95.otf
notionmanager/.config/fonts/coresansc/coresansc95it.otf
notionmanager/.config/sync_config.json
notionmanager/__init__.py
notionmanager/api.py
notionmanager/backends.py
notionmanager/cli.py
notionmanager/cloudinary_manager.py
notionmanager/config.py
notionmanager/heartbeat.py
notionmanager/notion.py
notionmanager/obsidian_config.json
notionmanager/supabase.py
notionmanager/update_covers.py
notionmanager/utils.py
notionmanager-0.1.28.dist-info/LICENSE
notionmanager-0.1.28.dist-info/METADATA
notionmanager-0.1.28.dist-info/WHEEL
notionmanager-0.1.28.dist-info/entry_points.txt
notionmanager-0.1.28.dist-info/RECORD
