Metadata-Version: 2.1
Name: notionmanager
Version: 0.1.28
Summary: A Python package for managing courses, projects, and directories with Notion integration.
Author: Suhail
Author-email: suhailece@gmail.com
Requires-Python: >=3.11,<4.0
Classifier: Programming Language :: Python :: 3
Classifier: Programming Language :: Python :: 3.11
Classifier: Programming Language :: Python :: 3.12
Classifier: Programming Language :: Python :: 3.13
Requires-Dist: cloudinary (>=1.42.2,<2.0.0)
Requires-Dist: notion-client (>=2.2.1,<3.0.0)
Requires-Dist: oauthmanager (>=0.1.1,<0.2.0)
Requires-Dist: prefect (>=3.2.12,<4)
Requires-Dist: prefect-github (>=0.3.0)
Requires-Dist: python-dotenv (>=1.0.1,<2.0.0)
Requires-Dist: requests (>=2.32.3,<3.0.0)
Requires-Dist: supabase (>=2.10.0,<3.0.0)
